rcl_lifecycle/_dummy.cpython-312-x86_64-linux-gnu.so
ros_rcl_lifecycle-10.1.3.data/data/include/rcl_lifecycle/rcl_lifecycle/data_types.h
ros_rcl_lifecycle-10.1.3.data/data/include/rcl_lifecycle/rcl_lifecycle/default_state_machine.h
ros_rcl_lifecycle-10.1.3.data/data/include/rcl_lifecycle/rcl_lifecycle/rcl_lifecycle.h
ros_rcl_lifecycle-10.1.3.data/data/include/rcl_lifecycle/rcl_lifecycle/transition_map.h
ros_rcl_lifecycle-10.1.3.data/data/include/rcl_lifecycle/rcl_lifecycle/version.h
ros_rcl_lifecycle-10.1.3.data/data/include/rcl_lifecycle/rcl_lifecycle/visibility_control.h
ros_rcl_lifecycle-10.1.3.data/data/lib/librcl_lifecycle.so
ros_rcl_lifecycle-10.1.3.data/data/share/ament_index/resource_index/package_run_dependencies/rcl_lifecycle
ros_rcl_lifecycle-10.1.3.data/data/share/ament_index/resource_index/packages/rcl_lifecycle
ros_rcl_lifecycle-10.1.3.data/data/share/ament_index/resource_index/parent_prefix_path/rcl_lifecycle
ros_rcl_lifecycle-10.1.3.data/data/share/rcl_lifecycle/local_setup.bash
ros_rcl_lifecycle-10.1.3.data/data/share/rcl_lifecycle/local_setup.dsv
ros_rcl_lifecycle-10.1.3.data/data/share/rcl_lifecycle/local_setup.sh
ros_rcl_lifecycle-10.1.3.data/data/share/rcl_lifecycle/local_setup.zsh
ros_rcl_lifecycle-10.1.3.data/data/share/rcl_lifecycle/package.dsv
ros_rcl_lifecycle-10.1.3.data/data/share/rcl_lifecycle/package.xml
ros_rcl_lifecycle-10.1.3.data/data/share/rcl_lifecycle/cmake/ament_cmake_export_dependencies-extras.cmake
ros_rcl_lifecycle-10.1.3.data/data/share/rcl_lifecycle/cmake/ament_cmake_export_include_directories-extras.cmake
ros_rcl_lifecycle-10.1.3.data/data/share/rcl_lifecycle/cmake/ament_cmake_export_libraries-extras.cmake
ros_rcl_lifecycle-10.1.3.data/data/share/rcl_lifecycle/cmake/ament_cmake_export_targets-extras.cmake
ros_rcl_lifecycle-10.1.3.data/data/share/rcl_lifecycle/cmake/rcl_lifecycleConfig-version.cmake
ros_rcl_lifecycle-10.1.3.data/data/share/rcl_lifecycle/cmake/rcl_lifecycleConfig.cmake
ros_rcl_lifecycle-10.1.3.dist-info/METADATA
ros_rcl_lifecycle-10.1.3.dist-info/WHEEL
ros_rcl_lifecycle-10.1.3.dist-info/top_level.txt
ros_rcl_lifecycle-10.1.3.dist-info/RECORD
