Metadata-Version: 2.4
Name: ros-rcl-lifecycle
Version: 10.1.3
Summary: ROS 2 package `rcl_lifecycle` provides core C functionality for managing lifecycle nodes in ROS 2 applications.
Requires-Dist: ros-rosidl-runtime-c~=4.9.5
Requires-Dist: ros-rmw~=7.8.2
Requires-Dist: ros-lifecycle-msgs~=2.3.0
Requires-Dist: ros-rcutils~=6.9.8
Requires-Dist: ros-rcl~=10.1.3
Requires-Dist: ros-tracetools~=8.6.0
Dynamic: description
Dynamic: description-content-type
Dynamic: requires-dist
Dynamic: summary
